confluent.py
py_confluent_cli-0.9.2.dist-info/LICENSE
py_confluent_cli-0.9.2.dist-info/METADATA
py_confluent_cli-0.9.2.dist-info/WHEEL
py_confluent_cli-0.9.2.dist-info/top_level.txt
py_confluent_cli-0.9.2.dist-info/RECORD
